{
  "version": 3,
  "middleware": {
    "/": {
      "files": [
        "server/edge/chunks/_717c1e95._.js",
        "server/edge/chunks/[root-of-the-server]__dc15d093._.js",
        "server/edge/chunks/edge-wrapper_ac7adf20.js"
      ],
      "name": "middleware",
      "page": "/",
      "matchers": [
        {
          "regexp": "^(?:\\/(_next\\/data\\/[^/]{1,}))?\\/admin(\\\\.json)?[\\/#\\?]?$",
          "originalSource": "/admin"
        },
        {
          "regexp": "^(?:\\/(_next\\/data\\/[^/]{1,}))?\\/admin(?:\\/((?:[^\\/#\\?]+?)(?:\\/(?:[^\\/#\\?]+?))*))?(\\\\.json)?[\\/#\\?]?$",
          "originalSource": "/admin/:path*"
        },
        {
          "regexp": "^(?:\\/(_next\\/data\\/[^/]{1,}))?\\/login(\\\\.json)?[\\/#\\?]?$",
          "originalSource": "/login"
        }
      ],
      "wasm": [],
      "assets": [],
      "env": {
        "__NEXT_BUILD_ID": "development",
        "NEXT_SERVER_ACTIONS_ENCRYPTION_KEY": "Zw5KNtKwMNTyOMe+8YAuqo9InLBx8l/f6iyXg5VSdGY=",
        "__NEXT_PREVIEW_MODE_ID": "4e6105fd5a72e931468c9e028e7e4ea7",
        "__NEXT_PREVIEW_MODE_ENCRYPTION_KEY": "34a86c24f2f59aa9586d8807db6653f19c65ddc2f6ef233c0ff25192950497fc",
        "__NEXT_PREVIEW_MODE_SIGNING_KEY": "59dd161690b91e0473ed38ad62a49c3425bd2ad520eb2c41041852406a30a353"
      }
    }
  },
  "sortedMiddleware": [
    "/"
  ],
  "functions": {}
}